concretefhe_frontend-0.0.10-py3.9-nspkg.pth
concretefhe/frontend/__init__.py
concretefhe/frontend/file.py
concretefhe_frontend-0.0.10.dist-info/LICENSE
concretefhe_frontend-0.0.10.dist-info/METADATA
concretefhe_frontend-0.0.10.dist-info/WHEEL
concretefhe_frontend-0.0.10.dist-info/namespace_packages.txt
concretefhe_frontend-0.0.10.dist-info/top_level.txt
concretefhe_frontend-0.0.10.dist-info/RECORD
